Metadata-Version: 2.1
Name: compareurls
Version: 1.0.1
Summary: Compare URLs by first normalizing them
Home-page: https://yoginth.com
Author: Yoginth
Author-email: me@yoginth.com
License: UNKNOWN
Project-URL: Patreon, https://www.patreon.com/yoginth
Project-URL: Source, https://gitlab.com/yoginth/compareurls
Platform: UNKNOWN
Classifier: Programming Language :: Python
Classifier: Natural Language :: English
Classifier: Environment :: Plugins
Classifier: Operating System :: OS Independent
Classifier: Intended Audience :: Developers
Classifier: License :: OSI Approved :: MIT License
